CHANGELOG.txt
LICENCE.txt
MANIFEST.in
README.txt
setup.py
monirulhasan/__init__.py
monirulhasan.egg-info/PKG-INFO
monirulhasan.egg-info/SOURCES.txt
monirulhasan.egg-info/dependency_links.txt
monirulhasan.egg-info/top_level.txt