Metadata-Version: 1.1
Name: monirulhasan
Version: 0.0.1
Summary: A very basic calculator
Home-page: UNKNOWN
Author: rakibul
Author-email: rakibul.fiverr@gmail.com
License: MIT
Keywords: calculator
Platform: UNKNOWN
Classifier: Development Status :: 5 - Production/Stable
Classifier: Intended Audience :: Education
Classifier: License :: OSI Approved :: MIT License
Classifier: Programming Language :: Python :: 3
